x3dase/__init__.py
x3dase/script.py
x3dase/tools.py
x3dase/visualize.py
x3dase/x3d.py
x3dase/css/style.css
x3dase/html/menu.html
x3dase/images/isosurface.png
x3dase/images/jupyter.png
x3dase/images/models.png
x3dase/images/polyhedra.png
x3dase/js/script.js
x3dase-1.1.4.dist-info/LICENSE
x3dase-1.1.4.dist-info/METADATA
x3dase-1.1.4.dist-info/WHEEL
x3dase-1.1.4.dist-info/top_level.txt
x3dase-1.1.4.dist-info/RECORD
