Metadata-Version: 2.1
Name: x3dase
Version: 1.1.4
Summary: Drawing and rendering atoms and molecules objects using X3DOM. X3dase can be used as a viewer for the molecule structure in the Jupyter notebook.
Home-page: https://github.com/superstar54/x3dase
Author: Xing Wang
Author-email: xingwang1991@gmail.com
License: GPL
Platform: UNKNOWN
Classifier: License :: OSI Approved :: GNU General Public License v3 (GPLv3)
Classifier: Programming Language :: Python :: 3
Classifier: Programming Language :: Python :: 3.8
Requires-Python: >=3
Requires-Dist: ase
Requires-Dist: numpy
Requires-Dist: scipy
